{
  "ok": true,
  "items": [
    {
      "source": "github-developers",
      "developer": "huggingface",
      "developer_url": "https://github.com/huggingface",
      "developer_followers": 63056,
      "developer_region": "global",
      "full_name": "huggingface/nanowhale",
      "url": "https://github.com/huggingface/nanowhale",
      "language": "Python",
      "stars": 105,
      "created_hours_ago": 53
    },
    {
      "source": "github-developers",
      "developer": "anthropics",
      "developer_url": "https://github.com/anthropics",
      "developer_followers": 54638,
      "developer_region": "global",
      "full_name": "anthropics/cwc-workshops",
      "url": "https://github.com/anthropics/cwc-workshops",
      "language": "TypeScript",
      "stars": 7,
      "created_hours_ago": 16
    },
    {
      "source": "github-developers",
      "developer": "steipete",
      "developer_url": "https://github.com/steipete",
      "developer_followers": 49322,
      "developer_region": "global",
      "full_name": "steipete/ghx",
      "url": "https://github.com/steipete/ghx",
      "description": "GitHub CLI Cache Proxy. Caching daemon for the gh CLI to prevent API rate limiting.",
      "language": null,
      "stars": 6,
      "created_hours_ago": 43
    },
    {
      "source": "github-developers",
      "developer": "hiteshchoudhary",
      "developer_url": "https://github.com/hiteshchoudhary",
      "developer_followers": 56847,
      "developer_region": "global",
      "full_name": "hiteshchoudhary/Masterji-home",
      "url": "https://github.com/hiteshchoudhary/Masterji-home",
      "language": "TypeScript",
      "stars": 5,
      "created_hours_ago": 44
    },
    {
      "source": "github-developers",
      "developer": "gamemann",
      "developer_url": "https://github.com/gamemann",
      "developer_followers": 28536,
      "developer_region": "global",
      "full_name": "gamemann/docker-ubuntu-xfce-with-gluetun",
      "url": "https://github.com/gamemann/docker-ubuntu-xfce-with-gluetun",
      "description": "A Docker Compose setup for running an Ubuntu XFCE desktop environment using Webtop with Gluetun VPN!",
      "language": "Dockerfile",
      "stars": 3,
      "created_hours_ago": 69
    },
    {
      "source": "github-developers",
      "developer": "ReVanced",
      "developer_url": "https://github.com/ReVanced",
      "developer_followers": 29348,
      "developer_region": "global",
      "full_name": "ReVanced/revanced-jadx-plugin",
      "url": "https://github.com/ReVanced/revanced-jadx-plugin",
      "description": "🩹 Plugin for JADX to assist with patches",
      "language": null,
      "stars": 1,
      "created_hours_ago": 46
    },
    {
      "source": "github-developers",
      "developer": "jserv",
      "developer_url": "https://github.com/jserv",
      "developer_followers": 4389,
      "developer_region": "taiwan",
      "full_name": "jserv/cellphone-prototype",
      "url": "https://github.com/jserv/cellphone-prototype",
      "description": " A phone UI demo for LVGL",
      "language": "C",
      "stars": 1,
      "created_hours_ago": 63
    },
    {
      "source": "github-developers",
      "developer": "roberthsu2003",
      "developer_url": "https://github.com/roberthsu2003",
      "developer_followers": 705,
      "developer_region": "taiwan",
      "full_name": "roberthsu2003/__11505_ai_tvdi__",
      "url": "https://github.com/roberthsu2003/__11505_ai_tvdi__",
      "description": "職能發展學院_11505_AI_協作程式開發班",
      "language": null,
      "stars": 1,
      "created_hours_ago": 42
    },
    {
      "source": "github-developers",
      "developer": "microsoft",
      "developer_url": "https://github.com/microsoft",
      "developer_followers": 118990,
      "developer_region": "global",
      "full_name": "microsoft/amplifier-bundle-evaluation",
      "url": "https://github.com/microsoft/amplifier-bundle-evaluation",
      "description": "evaluation bundle for the Amplifier project",
      "language": null,
      "stars": 0,
      "created_hours_ago": 53
    },
    {
      "source": "github-developers",
      "developer": "google",
      "developer_url": "https://github.com/google",
      "developer_followers": 71995,
      "developer_region": "global",
      "full_name": "google/ai-abap-assist-eclipse",
      "url": "https://github.com/google/ai-abap-assist-eclipse",
      "language": null,
      "stars": 0,
      "created_hours_ago": 0
    },
    {
      "source": "github-developers",
      "developer": "apple",
      "developer_url": "https://github.com/apple",
      "developer_followers": 36528,
      "developer_region": "global",
      "full_name": "apple/ml-headsup",
      "url": "https://github.com/apple/ml-headsup",
      "language": "HTML",
      "stars": 0,
      "created_hours_ago": 26
    },
    {
      "source": "github-developers",
      "developer": "vercel",
      "developer_url": "https://github.com/vercel",
      "developer_followers": 28010,
      "developer_region": "global",
      "full_name": "vercel/vc-runtime-lab",
      "url": "https://github.com/vercel/vc-runtime-lab",
      "language": "TypeScript",
      "stars": 0,
      "created_hours_ago": 4
    },
    {
      "source": "github-developers",
      "developer": "doggy8088",
      "developer_url": "https://github.com/doggy8088",
      "developer_followers": 4400,
      "developer_region": "taiwan",
      "full_name": "doggy8088/pdf-shrink",
      "url": "https://github.com/doggy8088/pdf-shrink",
      "description": "pdf-shrink：PDF 壓縮工具",
      "language": "Rust",
      "stars": 0,
      "created_hours_ago": 25
    },
    {
      "source": "github-developers",
      "developer": "peter279k",
      "developer_url": "https://github.com/peter279k",
      "developer_followers": 2146,
      "developer_region": "taiwan",
      "full_name": "peter279k/dynamic-values-system",
      "url": "https://github.com/peter279k/dynamic-values-system",
      "description": "Enterprise-grade real-time dynamic values system with military-grade security, WAF, rate limiting, and Redis cluster sup...",
      "language": null,
      "stars": 0,
      "created_hours_ago": 60
    },
    {
      "source": "github-developers",
      "developer": "CurtisChou-51",
      "developer_url": "https://github.com/CurtisChou-51",
      "developer_followers": 1030,
      "developer_region": "taiwan",
      "full_name": "CurtisChou-51/PatternFileCategorizer",
      "url": "https://github.com/CurtisChou-51/PatternFileCategorizer",
      "language": "C#",
      "stars": 0,
      "created_hours_ago": 52
    }
  ],
  "users_checked": 176
}
